flexfail/__init__.py
flexfail/_error_collector.py
flexfail/exceptions/__init__.py
flexfail-2.0.0.dist-info/LICENSE
flexfail-2.0.0.dist-info/METADATA
flexfail-2.0.0.dist-info/WHEEL
flexfail-2.0.0.dist-info/RECORD
