Metadata-Version: 2.3
Name: flexfail
Version: 2.0.0
Summary: Flexible failures collector with different collect strategies.
License: MIT
Author: endusol
Author-email: pdima.endusol@gmail.com
Requires-Python: >=3.9
Classifier: License :: OSI Approved :: MIT License
Classifier: Programming Language :: Python :: 3
Classifier: Programming Language :: Python :: 3.9
Classifier: Programming Language :: Python :: 3.10
Classifier: Programming Language :: Python :: 3.11
Classifier: Programming Language :: Python :: 3.12
Classifier: Programming Language :: Python :: 3.13
Project-URL: Homepage, https://github.com/endusol/flexfail
Project-URL: Issues, https://github.com/endusol/flexfail/issues
